cli_automation/.DS_Store
cli_automation/__init__.py
cli_automation/__main__.py
cli_automation/app_ssh.py
cli_automation/app_telnet.py
cli_automation/app_tunnel.py
cli_automation/cla.log
cli_automation/config.json
cli_automation/config_srv.py
cli_automation/datos/.DS_Store
cli_automation/datos/cla.png
cli_automation/datos/video-cla.png
cli_automation/examples/arista_eos_commands_file.json
cli_automation/examples/cisco_ios_commands_file.json
cli_automation/examples/cisco_nxos_commands_file.json
cli_automation/examples/cisco_xe_commands_file.json
cli_automation/examples/cisco_xr_commands_file.json
cli_automation/examples/extreme_exos_commands_file.json
cli_automation/examples/hosts_file.json
cli_automation/examples/huawei_commands_file.json
cli_automation/examples/huawei_vrp_commands_file.json
cli_automation/examples/juniper_junos_commands_file.json
cli_automation/examples/telnet_commands_example.json
cli_automation/examples/telnet_commands_structure.json
cli_automation/examples/vyos_commands_file.json
cli_automation/main.py
cli_automation/navigate.html
cli_automation/output.json
cli_automation/output.txt
cli_automation/ssh_hosts.json
cli_automation/ssh_pull.json
cli_automation/ssh_push.json
cli_automation/svc_enums.py
cli_automation/svc_files.py
cli_automation/svc_model.py
cli_automation/svc_progress.py
cli_automation/svc_proxy.py
cli_automation/svc_ssh.py
cli_automation/svc_telnet.py
cli_automation/svc_templates.py
cli_automation/svc_tunnel.py
cli_automation/telnet_hosts.json
cli_automation/telnet_push.json
cli_automation-1.6.2.dist-info/LICENSE
cli_automation-1.6.2.dist-info/METADATA
cli_automation-1.6.2.dist-info/WHEEL
cli_automation-1.6.2.dist-info/entry_points.txt
cli_automation-1.6.2.dist-info/RECORD
