Metadata-Version: 2.3
Name: cli-automation
Version: 1.6.2
Summary: Network Automation from the Command Line
License: GNU GENERAL PUBLIC LICENSE
Keywords: networking,automation,typer,cli,python
Author: Ed Scrimaglia
Author-email: edgardo.scrimaglia@gmail.com
Requires-Python: >=3.10, <4.0
Classifier: License :: Other/Proprietary License
Classifier: Programming Language :: Python :: 3
Classifier: Programming Language :: Python :: 3.10
Classifier: Programming Language :: Python :: 3.11
Classifier: Programming Language :: Python :: 3.12
Classifier: Programming Language :: Python :: 3.13
Requires-Dist: aiofiles (>=24.1.0,<25.0.0)
Requires-Dist: netmiko (==4.5.0)
Requires-Dist: ntc-templates (>=1.1.0,<8.0.0)
Requires-Dist: paramiko (>=2.6.0,<4.0.0)
Requires-Dist: pydantic (>=2.10.6,<3.0.0)
Requires-Dist: pysocks (>=1.7.1,<2.0.0)
Requires-Dist: requests (>=2.32.3,<3.0.0)
Requires-Dist: rich (>=13.9.4,<14.0.0)
Requires-Dist: textfsm (>=1.1.0,<2.0.0)
Requires-Dist: typer (>=0.15.1,<0.16.0)
